{"thingDefinitions":[{"id":"5d60ff12528bc031f3bb7721","def":"{\"v\":9,\"a\":[22,18],\"inc\":[[\"red-bs-cube\",\"5d602dbd52992b0619803d76\"],[\"blue-bs-cube\",\"5d60c9ee93d4ca523c955e2c\"],[\"blue-bs-cube 2\",\"5d60cf082ff33c061f2c4fc7\"],[\"bs-blue-right\",\"5d60f4f0c57f284d56dc355a\"],[\"bs-blue-left\",\"5d60ef0e528bc031f3bb771f\"],[\"bs-blue-right 2\",\"5d60fbfaf6584a63b407b609\"],[\"bs-blue-up\",\"5d60f061877b8552481113ef\"]],\"p\":[{\"b\":3,\"a\":[36],\"i\":[{\"t\":\"5d60febba9954e31e8dc4d36\",\"p\":[0.9981606,-0.0739405,0.004591204],\"r\":[0,270,270]}],\"s\":[{\"p\":[-0.8863201,0.01807991,0.04012895],\"r\":[270,180,0],\"s\":[0.1250453,0.1250129,0.1250285],\"c\":[0.1142856,0,1],\"b\":[\"when told start then become 2 in 10s\"]},{\"p\":[-0.9093906,-12.00698,0.01129913],\"r\":[270,180,0],\"s\":[0.1251202,0.1250199,0.1250973],\"c\":[0.1142856,0,1],\"b\":[\"when told resetpos then become 1\"]}]},{\"a\":[36],\"s\":[{\"p\":[-0.02911109,-1.053787,-0.1858217],\"r\":[270,180,0],\"s\":[0.1750363,0.1750187,0.1750514],\"c\":[0,1,0.3999999],\"b\":[\"when hears start song then tell  start\",\"when told start then become 2\"]},{\"p\":[-0.02911109,-1.053787,-0.1858217],\"r\":[270,180,0],\"s\":[0.1750363,0.1750187,0.1750514],\"c\":[1,0,0],\"b\":[\"when hears reset song then tell resetpos\",\"when told resetpos then become 1\"]}]},{\"t\":7,\"s\":[{\"p\":[-0.4273911,7.472744E-08,0],\"r\":[270,1.001791E-05,0],\"s\":[0.1750097,0.1750236,0.1750231],\"c\":[0,1,0.3999998],\"b\":[\"when told b3-red then emit gravity-free red-bs-cube with 2\",\"when told b3-blue then emit gravity-free blue-bs-cube 2 with 2\"]}]},{\"t\":7,\"s\":[{\"p\":[-0.03577232,-0.008129118,0.01631904],\"r\":[270,1.001791E-05,0],\"s\":[0.1750386,0.1751323,0.1751334],\"c\":[0,1,0.3999998],\"b\":[\"when told b2-red then emit gravity-free red-bs-cube with 2\",\"when told b2-blue then emit gravity-free blue-bs-cube 2 with 2\"]}]},{\"t\":7,\"s\":[{\"p\":[0.4016743,-6.705523E-08,-0.03860236],\"r\":[270,1.001791E-05,0],\"s\":[0.1750175,0.1750331,0.1750371],\"c\":[0,1,0.3999998],\"b\":[\"when told b1-red then emit gravity-free red-bs-cube with 2\",\"when told b1-blue then emit gravity-free blue-bs-cube 2 with 2\"]}]},{\"t\":7,\"a\":[37],\"s\":[{\"p\":[-1.4697,-8.834065,0.3818426],\"r\":[0,270,0],\"s\":[0.001,17.58196,0.1751692],\"c\":[0,1,1]},{\"p\":[-1.469699,-8.834064,0.3009024],\"r\":[-9.659349E-06,270,1.221333E-12],\"s\":[0.175155,17.58146,0.1751649],\"c\":[0,1,1]}]},{\"t\":7,\"a\":[37],\"s\":[{\"p\":[-1.462467,-8.845733,0.07350445],\"r\":[0,270,0],\"s\":[0.02148914,17.57775,0.1751281],\"c\":[0,1,1]}]},{\"t\":7,\"a\":[37],\"s\":[{\"p\":[-1.512465,-8.840704,-0.2987633],\"r\":[0,270,0],\"s\":[0.01428116,17.59002,0.1752312],\"c\":[0,1,1]},{\"p\":[-1.512465,-8.840699,-0.4746208],\"r\":[-9.659349E-06,270,1.221333E-12],\"s\":[0.175198,17.58935,0.1752284],\"c\":[0,1,1]}]},{\"t\":7,\"a\":[37],\"s\":[{\"p\":[-2.376354,-8.8407,-0.2874727],\"r\":[0,270,0],\"s\":[0.008932887,17.58893,0.1752232],\"c\":[0,1,1]}]},{\"t\":7,\"a\":[37],\"s\":[{\"p\":[-2.353601,-8.830114,0.08523178],\"r\":[0,270,0],\"s\":[0.01816335,17.58398,0.1751881],\"c\":[0,1,1]}]},{\"t\":7,\"a\":[37],\"s\":[{\"p\":[-2.395439,-8.845742,0.4554272],\"r\":[0,270,0],\"s\":[0.02901796,17.58234,0.1751766],\"c\":[0,1,1]}]},{\"t\":7,\"a\":[37],\"s\":[{\"p\":[-1.935305,-8.814837,0.4598064],\"r\":[0,270,0],\"s\":[0.02846134,17.5811,0.1751671],\"c\":[0,1,1]}]},{\"t\":7,\"a\":[37],\"s\":[{\"p\":[-1.927781,-8.845737,0.08413315],\"r\":[0,270,0],\"s\":[0.01788202,17.57998,0.1751532],\"c\":[0,1,1]}]},{\"t\":7,\"a\":[37],\"s\":[{\"p\":[-2.010846,-8.840703,-0.2900209],\"r\":[0,270,0],\"s\":[0.02507072,17.58914,0.1752263],\"c\":[0,1,1]}]},{\"t\":7,\"s\":[{\"p\":[-0.3861046,-0.0252828,0.5064946],\"r\":[270,89.99999,0],\"s\":[0.1750668,0.175118,0.1751035],\"c\":[0,1,0.3999996],\"b\":[\"when told c3-red then emit gravity-free red-bs-cube with 2\",\"when told c3-blue then emit gravity-free blue-bs-cube 2 with 2\"]}]},{\"t\":7,\"s\":[{\"p\":[-0.03573799,-0.0138883,0.4779935],\"r\":[270,1.001791E-05,0],\"s\":[0.175062,0.1751268,0.1751348],\"c\":[0,1,0.3999996],\"b\":[\"when told c2-red then emit gravity-free red-bs-cube with 2\",\"when told c2-blue then emit gravity-free blue-bs-cube 2 with 2\"]}]},{\"t\":7,\"s\":[{\"p\":[0.4089413,-0.009660661,0.4698302],\"r\":[270,1.001791E-05,0],\"s\":[0.1750355,0.1750994,0.1751085],\"c\":[0,1,0.3999996],\"b\":[\"when told c1-red then emit gravity-free red-bs-cube with 2\",\"when told c1-blue then emit gravity-free blue-bs-cube 2 with 2\"]}]},{\"t\":7,\"s\":[{\"p\":[-0.4230766,-5.960464E-08,-0.4615423],\"r\":[270,270,0],\"s\":[0.175093,0.1751142,0.1750792],\"c\":[0,1,0.3999996],\"b\":[\"when told a3-red then emit gravity-free red-bs-cube with 2\",\"when told a3-blue then emit gravity-free blue-bs-cube 2 with 2\"]}]},{\"t\":7,\"s\":[{\"p\":[-0.04211617,0.04991144,-0.4787692],\"r\":[270,270,0],\"s\":[0.1750603,0.1750767,0.1750511],\"c\":[0,1,0.3999995],\"b\":[\"when told a2-red then emit gravity-free red-bs-cube with 2\",\"when told a2-blue then emit gravity-free blue-bs-cube 2 with 2\"]}]},{\"t\":7,\"s\":[{\"p\":[0.3782425,-5.960464E-08,-0.4648741],\"r\":[270,90,0],\"s\":[0.1750399,0.1750724,0.1750636],\"c\":[0,1,0.3999996],\"b\":[\"when told a1-red then emit gravity-free red-bs-cube with 2\"]}]},{\"b\":4,\"a\":[37],\"s\":[{\"p\":[0.3839054,0.254342,-0.4591736],\"r\":[270,337.5,0],\"s\":[0.1250525,0.1250359,0.1250345],\"c\":[1,1,1],\"b\":[\"when told a1-bl-right then emit gravity-free bs-blue-right 2\",\"when told a1-blue-left then emit gravity-free bs-blue-left with 2\"]}]}]}"},{"id":"5d60f2131cd73f062d675f30","def":"{\"n\":\"blue-node-left\",\"v\":9,\"a\":[7,18,38,39],\"inc\":[[\"red-node-object\",\"5d5bac55492e5221b107ebe5\"],[\"red-node-object 2\",\"5d5bade0a3ccf31b4533fca6\"],[\"red\",\"5d5baa534e3a0d2b3799ec38\"],[\"red 2\",\"5d6035665b135f4d4f829ef3\"],[\"red 3\",\"5d60365bdaec9563aede292b\"],[\"red 4\",\"5d6036cae8753e4d50f88328\"],[\"red 5\",\"5d60374bf6584a63b407b5cc\"],[\"blue\",\"5d60c8cef107ab63ad7bc013\"],[\"blue 2\",\"5d60d069528bc031f3bb7717\"],[\"blue-left\",\"5d60d82ec57f284d56dc3559\"]],\"p\":[{\"b\":10,\"a\":[37],\"s\":[{\"p\":[0,0,0],\"r\":[0,0,0],\"s\":[0.0307006,0.03686644,0.03686662],\"c\":[0,0.3999996,1],\"b\":[\"when starts then become 2\"]},{\"p\":[0,0,0],\"r\":[-3.895342E-06,8.537735E-07,1.067217E-07],\"s\":[0.0307006,0.03686644,0.03686662],\"c\":[0,0.3999996,1],\"b\":[\"when starts then tell emit\",\"when told emit then emit gravity-free blue-left with 0\",\"when told emit then become 1\"]},{\"p\":[0,0,0],\"r\":[0,0,0],\"s\":[0.0307006,0.03686644,0.03686662],\"c\":[0,0.3999996,1]}]}]}"},{"id":"5d60df35528bc031f3bb771b","def":"{\"n\":\"blue-node-down\",\"v\":9,\"a\":[22,18,38,39],\"inc\":[[\"red-node-object\",\"5d5bac55492e5221b107ebe5\"],[\"red-node-object 2\",\"5d5bade0a3ccf31b4533fca6\"],[\"red\",\"5d5baa534e3a0d2b3799ec38\"],[\"red 2\",\"5d6035665b135f4d4f829ef3\"],[\"red 3\",\"5d60365bdaec9563aede292b\"],[\"red 4\",\"5d6036cae8753e4d50f88328\"],[\"red 5\",\"5d60374bf6584a63b407b5cc\"],[\"blue\",\"5d60c8cef107ab63ad7bc013\"],[\"blue 2\",\"5d60d069528bc031f3bb7717\"],[\"blue-left\",\"5d60d81ddaec9563aede2969\"],[\"blue-left 2\",\"5d60d82ec57f284d56dc3559\"],[\"blue-down\",\"5d60df01f107ab63ad7bc019\"]],\"p\":[{\"b\":10,\"a\":[37],\"s\":[{\"p\":[0,0,0],\"r\":[0,0,0],\"s\":[0.0307006,0.03686644,0.03686662],\"c\":[0,0.3999996,1],\"b\":[\"when starts then become 2\"]},{\"p\":[0,0,0],\"r\":[-3.895342E-06,8.537735E-07,1.067217E-07],\"s\":[0.0307006,0.03686644,0.03686662],\"c\":[0,0.3999996,1],\"b\":[\"when starts then tell emit\",\"when told emit then emit gravity-free blue-down with 0\",\"when told emit then become 1\"]},{\"p\":[0,0,0],\"r\":[0,0,0],\"s\":[0.0307006,0.03686644,0.03686662],\"c\":[0,0.3999996,1]}]}]}"},{"id":"5d60febba9954e31e8dc4d36","def":"{\"v\":9,\"a\":[22,18],\"inc\":[[\"red\",\"5d5ba725492e5221b107ebe4\"],[\"red-bs-cube\",\"5d5d676593d4ca523c955d5b\"],[\"red-bs-cube 2\",\"5d5d680e54786f63ba32e102\"],[\"red-bs-cube 3\",\"5d5d6a3df6584a63b407b54b\"],[\"red-bs-cube 4\",\"5d6012bf52f5ed061dc5a73b\"]],\"p\":[{\"t\":7,\"s\":[{\"p\":[-0.3971016,0,7.100731E-08],\"r\":[2.544444E-13,8.537737E-06,-3.415095E-06],\"s\":[0.3791136,0.001000033,0.4303621],\"c\":[0,0.7428566,1],\"b\":[\"when touches red then tell c2-red\",\"when touches red then tell c2-touched\",\"when told c2-touched then become 2\",\"when touches blue then tell c2-blue\",\"when touches blue then tell c2-touched\"]},{\"p\":[-0.3971016,0,7.100731E-08],\"r\":[2.544444E-13,8.537737E-06,-3.415095E-06],\"s\":[0.3791136,0.001000033,0.4303621],\"c\":[1,0,0],\"b\":[\"when starts then become 1 in 0.2s\"]}]},{\"t\":7,\"s\":[{\"p\":[-0.4047035,0,-0.4508952],\"r\":[2.544444E-13,8.537737E-06,-3.415095E-06],\"s\":[0.3791434,0.001000338,0.4304487],\"c\":[0,0.7428566,1],\"b\":[\"when touches red then tell c3-red\",\"when touches red then tell c3-touched\",\"when told c3-touched then become 2\",\"when touches blue then tell c3-blue\",\"when touches blue then tell c3-touched\"]},{\"p\":[-0.4047035,0,-0.4508952],\"r\":[2.544444E-13,8.537737E-06,-3.415095E-06],\"s\":[0.3791434,0.001000338,0.4304487],\"c\":[1,0,0],\"b\":[\"when starts then become 1 in 0.2s\"]}]},{\"t\":7,\"s\":[{\"p\":[0.0004028678,0,-0.4303408],\"r\":[0,90.00001,0],\"s\":[0.379151,0.001000278,0.3695471],\"c\":[0,0.7428566,1],\"b\":[\"when touches red then tell b3-red\",\"when touches red then tell b3-touched\",\"when told b3-touched then become 2\",\"when touches blue then tell b3-blue\",\"when touches blue then tell b3-touched\"]},{\"p\":[0.0004028678,0,-0.4303408],\"r\":[0,90.00001,0],\"s\":[0.379151,0.001000278,0.3695471],\"c\":[1,0,0],\"b\":[\"when starts then become 1 in 0.2s\"]}]},{\"t\":7,\"s\":[{\"p\":[-9.313226E-10,0,-0.007511139],\"r\":[0,0,0],\"s\":[0.3790879,0.001000125,0.430338],\"c\":[0,0.7428566,1],\"b\":[\"when touches red then tell b2-red\",\"when touches red then tell b2-touched\",\"when told b2-touched then become 2\",\"when touches blue then tell b2-blue\",\"when touches blue then tell b2-touched\"]},{\"p\":[-9.313226E-10,0,-0.007511139],\"r\":[0,0,0],\"s\":[0.3790879,0.001000125,0.430338],\"c\":[1,0,0],\"b\":[\"when starts then become 1 in 0.2s\"]}]},{\"t\":7,\"s\":[{\"p\":[0.3945097,0,-0.4504195],\"r\":[0,0,0],\"s\":[0.3791382,0.001000221,0.4304501],\"c\":[0,0.7428566,1],\"b\":[\"when touches red then tell a3-red\",\"when touches red then tell a3-touched\",\"when told a3-touched then become 2\",\"when touches blue then tell a3-blue\",\"when touches blue then tell a3-touched\"]},{\"p\":[0.3945097,0,-0.4504195],\"r\":[0,0,0],\"s\":[0.3791382,0.001000221,0.4304501],\"c\":[1,0,0],\"b\":[\"when starts then become 1 in 0.2s\"]}]},{\"t\":7,\"s\":[{\"p\":[0.3945098,0,-0.01305301],\"r\":[0,0,0],\"s\":[0.3791596,0.00100033,0.4304173],\"c\":[0,0.7428566,1],\"b\":[\"when touches red then tell a2-red\",\"when touches red then tell a2-touched\",\"when told a2-touched then become 2\",\"when touches blue then tell a2-blue\",\"when touches blue then tell a2-touched\"]},{\"p\":[0.3945098,0,-0.01305301],\"r\":[0,0,0],\"s\":[0.3791596,0.00100033,0.4304173],\"c\":[1,0,0],\"b\":[\"when starts then become 1 in 0.2s\"]},{\"p\":[0.3945098,0,-0.01305301],\"r\":[0,0,0],\"s\":[0.3791596,0.00100033,0.4304173],\"c\":[0,0.7428566,1]}]},{\"t\":7,\"s\":[{\"p\":[0.3945099,0,0.4339942],\"r\":[2.544444E-13,8.537737E-06,-3.415095E-06],\"s\":[0.3791968,0.00100042,0.430416],\"c\":[0,0.7428566,1],\"b\":[\"when touches red then tell a1-red\",\"when told a1-touched then become 2\",\"when touches blue-left then tell a1-blue-left, tell a1-touched\",\"when touches blue-right then tell a1-bl-right, tell a1-touched\",\"when touches blue-up then tell a1-blue-up, tell a1-touched\",\"when touches blue-down then tell a1-blue-down, tell a1-touched\"]},{\"p\":[0.3945099,0,0.4339942],\"r\":[2.544444E-13,8.537737E-06,-3.415095E-06],\"s\":[0.3791968,0.00100042,0.430416],\"c\":[1,0,0],\"b\":[\"when starts then become 1 in 0.2s\"]}]},{\"a\":[8],\"s\":[{\"p\":[-0.1666851,-11.02169,-7.165626],\"r\":[0,180,0],\"s\":[0.1750049,0.1750041,0.1750027],\"c\":[1,1,1]},{\"p\":[-0.1666851,-11.02169,-7.165626],\"r\":[0,180,0],\"s\":[0.1750049,0.1750041,0.1750027],\"c\":[1,1,1]}]},{\"t\":7,\"s\":[{\"p\":[0.008727133,0.005112648,0.4527521],\"r\":[2.544444E-13,8.537737E-06,-3.415095E-06],\"s\":[0.379157,0.001000341,0.4303402],\"c\":[0,0.7428566,1],\"b\":[\"when touches red then tell b1-red\",\"when touches red then tell b1-touched\",\"when told b1-touched then become 2\",\"when touches blue then tell b1-blue\",\"when touches blue then tell b1-touched\"]},{\"p\":[0.008727133,0.005112648,0.4527521],\"r\":[2.544444E-13,8.537737E-06,-3.415095E-06],\"s\":[0.379157,0.001000341,0.4303402],\"c\":[1,0,0],\"b\":[\"when starts then become 1 in 0.2s\"]}]},{\"t\":7,\"s\":[{\"p\":[-0.4036808,0.005157471,0.4516135],\"r\":[0,0,0],\"s\":[0.3791656,0.001000254,0.4304245],\"c\":[0,0.7428566,1],\"b\":[\"when touches red then tell c1-red\",\"when touches red then tell c1-touched\",\"when told c1-touched then become 2\",\"when touches blue then tell c1-blue\",\"when touches blue then tell c1-touched\"]},{\"p\":[-0.4036808,0,0.4516135],\"r\":[0,0,0],\"s\":[0.3791423,0.001000179,0.4303874],\"c\":[1,0,0],\"b\":[\"when starts then become 1 in 0.2s\"]}]}]}"}],"serveTime":17}